colors/__init__.py
colors/colors.py
colors/version.py
Py_Colors-0.2.dist-info/LICENSE
Py_Colors-0.2.dist-info/METADATA
Py_Colors-0.2.dist-info/WHEEL
Py_Colors-0.2.dist-info/top_level.txt
Py_Colors-0.2.dist-info/RECORD
