Metadata-Version: 2.1
Name: Py-Colors
Version: 0.2
Summary: Library For Coloring And Formatting Terminal
Home-page: https://github.com/pmk456/Py-Colors
Author: Patan Musthakheem
Author-email: patanmusthakheem786@gmail.com
License: Apache 2.0
Project-URL: Documentation, https://github.com/pmk456/Py-Colors
Project-URL: Source, https://github.com/pmk456/Py-Colors
Project-URL: Tracker, https://github.com/pmk456/Py-Colors/issues
Platform: UNKNOWN
Classifier: License :: OSI Approved :: Apache Software License
Classifier: Intended Audience :: Developers
Classifier: Programming Language :: Python :: 3
Requires-Python: >=3.5
License-File: LICENSE
